tool/__init__.py
tool/ext.py
tool/tld_lists.txt
extractor_v02-0.0.11.dist-info/METADATA
extractor_v02-0.0.11.dist-info/WHEEL
extractor_v02-0.0.11.dist-info/top_level.txt
extractor_v02-0.0.11.dist-info/RECORD
