Metadata-Version: 2.1
Name: extractor-v02
Version: 0.0.11
Summary: My first Python package
Home-page: UNKNOWN
Author: Jason Dsouza
Author-email: ilyaskaya.2323@gmail.com
License: UNKNOWN
Keywords: python,first package
Platform: UNKNOWN
Classifier: Development Status :: 3 - Alpha
Classifier: Intended Audience :: Education
Classifier: Programming Language :: Python :: 2
Classifier: Programming Language :: Python :: 3
Classifier: Operating System :: MacOS :: MacOS X
Classifier: Operating System :: Microsoft :: Windows
Requires-Dist: tldextract
